{"type":"node_created","timestamp":"2026-02-08T12:05:12.679463443Z","node":{"id":"1.4","type":"claim","statement":"KEY LEMMA (Phi via derivative formula): Using MSS_derivative_formula, r'(x) = n*(p^{(1)} ⊞_{n-1} q^{(1)})(x). Since H_r(lambda_i) = r'(lambda_i)/(2r'(lambda_i)), and r'(lambda_i) can be expressed via the roots gamma_1,...,gamma_{n-1} of r' (which are roots of p^{(1)} ⊞_{n-1} q^{(1)}), we obtain Phi_n(r) = sum_{i=1}^n [sum_{k=1}^{n-1} 1/(lambda_i - gamma_k) - sum_{j!=i} 1/(lambda_i - lambda_j)]^2 / 4.","inference":"assumption","workflow_state":"available","epistemic_state":"pending","taint_state":"unresolved","content_hash":"7815842945bcb5cd9762b67efd9eb401216c50d76d1a185e3089c43d862056c7","created":"2026-02-08T12:05:12.679452979Z","claimed_at":"0001-01-01T00:00:00Z"}}