{"type":"node_created","timestamp":"2026-02-08T22:35:06.616367891Z","node":{"id":"1.6.4.1","type":"claim","statement":"(Candidate measure rho is well-defined) Define R(phi) := exp(Psi^{ren}(phi)) / Z where Z := E_mu[exp(Psi^{ren})] and Psi^{ren}(phi) = 4 lambda \u003cpsi, :phi^3:\u003e - 6 lambda \u003cpsi^2, :phi^2:\u003e + 4 lambda \u003cpsi^3, phi\u003e + \u003c(-Delta+m^2)psi, phi\u003e (node 1.5.1). Define the probability measure rho on C^{-1/2-delta}(T^3) by d(rho)/d(mu) = R. By node 1.6.3.3: (a) 0 \u003c Z \u003c infinity, so R is well-defined; (b) E_mu[R] = 1, so rho is a probability measure; (c) R \u003e 0 mu-a.s. (since exp(Psi^{ren}) \u003e 0 and Psi^{ren} is finite mu-a.s.). We will show T_psi*mu = rho.","inference":"by_definition","workflow_state":"available","epistemic_state":"pending","taint_state":"unresolved","content_hash":"a05d26ea38f99802bfb9929ea3684902f4939dfbd9f2c34078104d219cbc7e99","created":"2026-02-08T22:35:06.61636586Z","claimed_at":"0001-01-01T00:00:00Z"}}